hs2p/__init__.py
hs2p/sampling.py
hs2p/tiling.py
hs2p/configs/__init__.py
hs2p/configs/default.yaml
hs2p/utils/__init__.py
hs2p/utils/config.py
hs2p/utils/log_utils.py
hs2p/utils/utils.py
hs2p/wsi/__init__.py
hs2p/wsi/utils.py
hs2p/wsi/wsi.py
hs2p-1.1.0.dist-info/licenses/LICENSE
hs2p-1.1.0.dist-info/METADATA
hs2p-1.1.0.dist-info/WHEEL
hs2p-1.1.0.dist-info/top_level.txt
hs2p-1.1.0.dist-info/RECORD
