Metadata-Version: 2.4
Name: hs2p
Version: 1.1.0
Summary: Optimized slide tiling library for histopathology
Home-page: https://github.com/clemsgrs/hs2p
Author: Clément Grisi
Author-email: clement.grisi@radboudumc.nl
Project-URL: Bug Tracker, https://github.com/clemsgrs/hs2p/issues
Platform: unix
Platform: linux
Platform: osx
Platform: cygwin
Platform: win32
Classifier: Programming Language :: Python :: 3
Classifier: Programming Language :: Python :: 3 :: Only
Classifier: Programming Language :: Python :: 3.10
Classifier: Programming Language :: Python :: 3.11
Classifier: Programming Language :: Python :: 3.12
Classifier: Programming Language :: Python :: 3.13
Requires-Python: >=3.10
License-File: LICENSE
Requires-Dist: omegaconf
Requires-Dist: numpy<2
Requires-Dist: pandas
Requires-Dist: h5py
Requires-Dist: tqdm
Requires-Dist: wandb
Requires-Dist: pillow
Requires-Dist: matplotlib
Requires-Dist: opencv-python
Requires-Dist: wholeslidedata
Provides-Extra: testing
Requires-Dist: pytest>=6.0; extra == "testing"
Requires-Dist: pytest-cov>=2.0; extra == "testing"
Requires-Dist: mypy>=0.910; extra == "testing"
Requires-Dist: flake8>=3.9; extra == "testing"
Requires-Dist: tox>=3.24; extra == "testing"
Dynamic: author-email
Dynamic: description
Dynamic: description-content-type
Dynamic: home-page
Dynamic: license-file
Dynamic: project-url
